morningstarFetcher/__init__.py
morningstarFetcher/screener.py
morningstarFetcher/search.py
morningstarFetcher/security.py
morningstarFetcher/queries/__init__.py
morningstarFetcher/queries/etf_queries.py
morningstarFetcher/queries/fund_queries.py
morningstarFetcher/queries/stock_queries.py
morningstarFetcher/utils/__init__.py
morningstarFetcher/utils/async_helpers.py
morningstarFetcher/utils/filtering.py
morningstarFetcher/utils/requests.py
morningstarFetcher/utils/screener_utils.py
morningstarfetcher-7.0.1.dist-info/licenses/LICENSE
morningstarfetcher-7.0.1.dist-info/METADATA
morningstarfetcher-7.0.1.dist-info/WHEEL
morningstarfetcher-7.0.1.dist-info/top_level.txt
morningstarfetcher-7.0.1.dist-info/RECORD
