Metadata-Version: 2.4
Name: morningstarFetcher
Version: 7.0.1
Summary: Morningstar scraping utilities
Author: nndjoli
Requires-Python: >=3.10
License-File: LICENSE
Requires-Dist: httpx
Requires-Dist: pandas
Requires-Dist: ua_generator
Requires-Dist: nest_asyncio
Dynamic: license-file
